normal_grain_merge/__init__.py
normal_grain_merge/kernel_kind.py
normal_grain_merge/normal_grain_merge.c
normal_grain_merge/normal_grain_merge.cpython-38-x86_64-linux-gnu.so
normal_grain_merge/normal_grain_merge.pyi
normal_grain_merge-0.1.2.dist-info/LICENSE
normal_grain_merge-0.1.2.dist-info/METADATA
normal_grain_merge-0.1.2.dist-info/WHEEL
normal_grain_merge-0.1.2.dist-info/top_level.txt
normal_grain_merge-0.1.2.dist-info/RECORD
