Metadata-Version: 2.1
Name: normal_grain_merge
Version: 0.1.2
Summary: Fused normal and grain merge C extension
Author: Samuel Howard
License: MIT
Project-URL: Homepage, https://github.com/samhaswon/normal_grain_merge
Project-URL: Bug Tracker, https://github.com/samhaswon/normal_grain_merge/issues
Keywords: image,processing
Classifier: Programming Language :: Python :: 3
Classifier: Programming Language :: C
Classifier: Operating System :: OS Independent
Requires-Python: >=3.8
License-File: LICENSE
Requires-Dist: numpy<2.3.0
